ntree/__init__.py
ntree/libntree.py
ntree-0.1.1.dist-info/METADATA
ntree-0.1.1.dist-info/WHEEL
ntree-0.1.1.dist-info/entry_points.txt
ntree-0.1.1.dist-info/top_level.txt
ntree-0.1.1.dist-info/RECORD
