Metadata-Version: 2.4
Name: ntree
Version: 0.1.1
Summary: A better version of the Linux tree command in Python
Author: Vijay Satheesh
Requires-Python: >=3.6
Requires-Dist: humanize
Dynamic: author
Dynamic: requires-dist
Dynamic: requires-python
Dynamic: summary
